vocals/__init__.py
vocals/audio_processor.py
vocals/cli.py
vocals/client.py
vocals/config.py
vocals/testing.py
vocals/token_manager.py
vocals/types.py
vocals/utils.py
vocals/websocket_client.py
vocals/wstoken.py
vocals-1.0.984.dist-info/licenses/LICENSE
vocals-1.0.984.dist-info/METADATA
vocals-1.0.984.dist-info/WHEEL
vocals-1.0.984.dist-info/entry_points.txt
vocals-1.0.984.dist-info/top_level.txt
vocals-1.0.984.dist-info/RECORD
