Metadata-Version: 2.4
Name: vocals
Version: 1.0.984
Summary: A Python SDK for voice processing and real-time audio communication
Home-page: https://github.com/hairetsucodes/vocals-sdk-python
Author: Vocals Team
Author-email: support@vocals.dev
Project-URL: Bug Reports, https://github.com/vocals/vocals-sdk-python/issues
Project-URL: Source, https://github.com/vocals/vocals-sdk-python
Project-URL: Documentation, https://docs.vocals.dev
Keywords: vocals,audio,speech,websocket,real-time,voice processing
Classifier: Development Status :: 4 - Beta
Classifier: Intended Audience :: Developers
Classifier: License :: OSI Approved :: MIT License
Classifier: Operating System :: OS Independent
Classifier: Programming Language :: Python :: 3
Classifier: Programming Language :: Python :: 3.8
Classifier: Programming Language :: Python :: 3.9
Classifier: Programming Language :: Python :: 3.10
Classifier: Programming Language :: Python :: 3.11
Classifier: Programming Language :: Python :: 3.12
Classifier: Topic :: Software Development :: Libraries :: Python Modules
Classifier: Topic :: Communications
Classifier: Topic :: Multimedia :: Sound/Audio
Requires-Python: >=3.8
License-File: LICENSE
Requires-Dist: aiohttp>=3.8.0
Requires-Dist: websockets>=11.0.0
Requires-Dist: sounddevice>=0.4.6
Requires-Dist: numpy>=1.21.0
Requires-Dist: PyJWT>=2.8.0
Requires-Dist: python-dotenv>=1.0.0
Requires-Dist: typing-extensions>=4.0.0
Requires-Dist: pyaudio>=0.2.11
Requires-Dist: soundfile>=0.12.1
Requires-Dist: click>=8.0.0
Requires-Dist: psutil>=5.9.0
Requires-Dist: matplotlib>=3.5.0
Dynamic: author
Dynamic: author-email
Dynamic: classifier
Dynamic: description
Dynamic: description-content-type
Dynamic: home-page
Dynamic: keywords
Dynamic: license-file
Dynamic: project-url
Dynamic: requires-dist
Dynamic: requires-python
Dynamic: summary
